toga_chart/__init__.py
toga_chart/chart.py
toga_chart-0.2.1.dist-info/licenses/AUTHORS
toga_chart-0.2.1.dist-info/licenses/LICENSE
toga_chart-0.2.1.dist-info/METADATA
toga_chart-0.2.1.dist-info/WHEEL
toga_chart-0.2.1.dist-info/top_level.txt
toga_chart-0.2.1.dist-info/RECORD
