Metadata-Version: 2.4
Name: toga-chart
Version: 0.2.1
Summary: A Toga matplotlib backend.
Author-email: Russell Keith-Magee <russell@keith-magee.com>
Maintainer-email: BeeWare Team <team@beeware.org>
License: New BSD
Project-URL: Homepage, https://github.com/beeware/toga-chart
Project-URL: Funding, https://beeware.org/contributing/membership/
Project-URL: Documentation, https://toga-chart.readthedocs.io/en/latest/
Project-URL: Tracker, https://github.com/beeware/toga-chart/issues
Project-URL: Source, https://github.com/beeware/toga-chart
Keywords: matplotlib,toga
Classifier: Development Status :: 4 - Beta
Classifier: Intended Audience :: Developers
Classifier: License :: OSI Approved :: BSD License
Classifier: Operating System :: OS Independent
Classifier: Programming Language :: Python :: 3
Classifier: Programming Language :: Python :: 3.9
Classifier: Programming Language :: Python :: 3.10
Classifier: Programming Language :: Python :: 3.11
Classifier: Programming Language :: Python :: 3.12
Classifier: Programming Language :: Python :: 3.13
Classifier: Programming Language :: Python :: 3 :: Only
Classifier: Topic :: Software Development
Classifier: Topic :: Software Development :: User Interfaces
Requires-Python: >=3.9
License-File: LICENSE
License-File: AUTHORS
Requires-Dist: matplotlib>=3.9.0
Requires-Dist: toga-core<0.6.0,>=0.5.0
Provides-Extra: dev
Requires-Dist: pre-commit==4.2.0; extra == "dev"
Requires-Dist: pytest==8.3.5; extra == "dev"
Requires-Dist: setuptools_scm==8.2.0; extra == "dev"
Requires-Dist: tox==4.25.0; extra == "dev"
Requires-Dist: toga-dummy<0.6.0,>=0.5.0; extra == "dev"
Provides-Extra: docs
Requires-Dist: furo==2024.8.6; extra == "docs"
Requires-Dist: pyenchant==3.2.2; extra == "docs"
Requires-Dist: sphinx==8.2.3; extra == "docs"
Requires-Dist: sphinx_tabs==3.4.7; extra == "docs"
Requires-Dist: sphinx-autobuild==2024.10.3; extra == "docs"
Requires-Dist: sphinx-copybutton==0.5.2; extra == "docs"
Requires-Dist: sphinxcontrib-spelling==8.0.1; extra == "docs"
Dynamic: license-file
